unlimited_classifier/__init__.py
unlimited_classifier/labels_trie.pyx
unlimited_classifier/labels_trie.pyxbld
unlimited_classifier/main.py
unlimited_classifier/scorer.py
unlimited_classifier/trie.cpp
unlimited_classifier/trie.h
unlimited_classifier/trie.pxd
unlimited_classifier-0.0.3.dist-info/LICENSE
unlimited_classifier-0.0.3.dist-info/METADATA
unlimited_classifier-0.0.3.dist-info/WHEEL
unlimited_classifier-0.0.3.dist-info/RECORD
