Metadata-Version: 2.1
Name: unlimited-classifier
Version: 0.0.3
Summary: Universal text classifier for generative models
License: Apache-2.0
Author: knowledgator.com
Requires-Python: >=3.8.0,<4.0.0
Classifier: License :: OSI Approved :: Apache Software License
Classifier: Programming Language :: Python :: 3
Classifier: Programming Language :: Python :: 3.8
Classifier: Programming Language :: Python :: 3.9
Classifier: Programming Language :: Python :: 3.10
Classifier: Programming Language :: Python :: 3.11
Classifier: Programming Language :: Python :: 3.12
Requires-Dist: accelerate (>=0.30.1)
Requires-Dist: bitsandbytes (>=0.40.1)
Requires-Dist: torch (>=1.10.0)
Requires-Dist: transformers (>=4.30.0)
